mypythonprojectcli/__cli__.py
mypythonprojectcli/__init__.py
mypythonprojectcli/cli/__init__.py
mypythonprojectcli/cli/cli.py
mypythonprojectcli/cli/prebuild.py
mypythonprojectcli/cli/pyproject.py
mypythonprojectcli/cli/utils.py
mypythonprojectcli/sample_module_a/__init__.py
mypythonprojectcli/sample_module_a/sample_module_a.py
mypythonprojectcli/sample_module_b/__init__.py
mypythonprojectcli/sample_module_b/sample_module_b.py
mypythonprojectcli/cli/header.json
mypythonprojectcli/cli/help.json
mypythonprojectcli/cli/modules.json
mypythonprojectcli/cli/template.json
mypythonprojectcli-1.0.0.0.dist-info/METADATA
mypythonprojectcli-1.0.0.0.dist-info/WHEEL
mypythonprojectcli-1.0.0.0.dist-info/entry_points.txt
mypythonprojectcli-1.0.0.0.dist-info/licenses/LICENSE
mypythonprojectcli-1.0.0.0.dist-info/RECORD
